pylacc/__init__.py
pylacc/circuit.py
pylacc-0.0.3.dist-info/METADATA
pylacc-0.0.3.dist-info/WHEEL
pylacc-0.0.3.dist-info/licenses/LICENSE
pylacc-0.0.3.dist-info/RECORD
