Metadata-Version: 2.3
Name: pylacc
Version: 0.0.3
Summary: Python Linear Analog Circuit Caclulator
Project-URL: Homepage, https://github.com/deckar01/pylacc
Author-email: Jared Deckard <jared@shademaps.com>
License-File: LICENSE
Classifier: Environment :: Handhelds/PDA's
Classifier: Intended Audience :: Education
Classifier: License :: OSI Approved :: MIT License
Classifier: Operating System :: OS Independent
Classifier: Programming Language :: Python :: 3
Requires-Python: >=3.4
